LICENSE
README.rst
requirements.txt
setup.cfg
setup.py
usage.png
snip_my_video/__init__.py
snip_my_video/__main__.py
snip_my_video.egg-info/PKG-INFO
snip_my_video.egg-info/SOURCES.txt
snip_my_video.egg-info/dependency_links.txt
snip_my_video.egg-info/entry_points.txt
snip_my_video.egg-info/requires.txt
snip_my_video.egg-info/top_level.txt