Metadata-Version: 1.0
Name: snip-my-video
Version: 0.1.1
Summary: Snip or cut a segment and render a subclip of a video clip
Home-page: https://github.com/rascoro1/SnipMyVideo
Author: jtara1
Author-email: UNKNOWN
License: UNKNOWN
Platform: UNKNOWN
